fastapi_crudrouter/__init__.py
fastapi_crudrouter/_version.py
fastapi_crudrouter/core/__init__.py
fastapi_crudrouter/core/_base.py
fastapi_crudrouter/core/_types.py
fastapi_crudrouter/core/_utils.py
fastapi_crudrouter/core/databases.py
fastapi_crudrouter/core/gino_starlette.py
fastapi_crudrouter/core/mem.py
fastapi_crudrouter/core/ormar.py
fastapi_crudrouter/core/sqlalchemy.py
fastapi_crudrouter/core/tortoise.py
fastapi_crudrouter_as3445-0.8.8.dist-info/LICENSE
fastapi_crudrouter_as3445-0.8.8.dist-info/METADATA
fastapi_crudrouter_as3445-0.8.8.dist-info/WHEEL
fastapi_crudrouter_as3445-0.8.8.dist-info/top_level.txt
fastapi_crudrouter_as3445-0.8.8.dist-info/RECORD
